LICENSE
MANIFEST.in
README.md
setup.py
pachira_python.egg-info/PKG-INFO
pachira_python.egg-info/SOURCES.txt
pachira_python.egg-info/dependency_links.txt
pachira_python.egg-info/not-zip-safe
pachira_python.egg-info/requires.txt
pachira_python.egg-info/top_level.txt
python/prod/__init__.py
python/prod/abi/__init__.py
python/prod/abi/abi_load.py
python/prod/configs/ERC20MockDecimals.json
python/prod/configs/pachira/IUniswapV2Pair.json
python/prod/configs/pachira/MintableRCIndexedYieldLinearExitPoolStudy.json
python/prod/configs/pachira/MintableRCStudy.json
python/prod/configs/pachira/UniV2IndexedYieldLinearExitPool.json
python/prod/configs/sushi/UniswapV2Factory.json
python/prod/configs/sushi/UniswapV2Pair.json
python/prod/configs/sushi/UniswapV2Router02.json
python/prod/configs/uniswap_v3/UniswapV3Factory.json
python/prod/configs/uniswap_v3/UniswapV3Pool.json
python/prod/contract/__utils__.py
python/prod/contract/deploy.py
python/prod/contract/view.py
python/prod/data/__init__.py
python/prod/data/chain_reorganization_resolution.py
python/prod/data/filter.py
python/prod/data/pair.py
python/prod/data/reorganization_monitor.py
python/prod/data/token_details.py
python/prod/enums/__init__.py
python/prod/enums/contracts_enum.py
python/prod/enums/event_type_enum.py
python/prod/enums/init_event_enum.py
python/prod/enums/nets_enum.py
python/prod/enums/platforms_enum.py
python/prod/enums/rpcs_enum.py
python/prod/event/__init__.py
python/prod/event/burn_event.py
python/prod/event/create_event.py
python/prod/event/event.py
python/prod/event/mint_event.py
python/prod/event/swap_event.py
python/prod/event/sync_event.py
python/prod/event/transfer_event.py
python/prod/event/process/__init__.py
python/prod/event/process/read_events.py
python/prod/event/process/retrieve_events.py
python/prod/event/tools/__init__.py
python/prod/event/tools/chain_reorganization_detection.py
python/prod/event/tools/conversion.py
python/prod/event/tools/log_context.py
python/prod/event/tools/log_result.py
python/prod/event/tools/rpc_reorganization_monitor.py
python/prod/token/__init__.py
python/prod/token/token.py
python/prod/uniswap_v2/__init__.py
python/prod/uniswap_v2/fetch_pair_details.py
python/prod/utils/__init__.py
