Metadata-Version: 2.1
Name: pachira-python
Version: 0.0.2
Summary: Python library for Pachira on DeFi, data research and integration
Home-page: https://github.com/SYS-Labs
Author: icmoore
Author-email: icmoore@syscoin.org
License: MIT
License-File: LICENSE
Requires-Dist: web3
Requires-Dist: eth_abi
Requires-Dist: eth_typing
Requires-Dist: eth_tester
Requires-Dist: eth_bloom
Requires-Dist: eth_utils
Requires-Dist: web3-ethereum-defi
Requires-Dist: hexbytes
Requires-Dist: pandas
